gradio2api/__init__.py
gradio2api/aggregator.py
gradio2api/cli.py
gradio2api/cli_remote.py
gradio2api/clients_aggregator.py
gradio2api/gr_application.py
gradio2api/gr_fastapi.py
gradio2api/gr_types/__init__.py
gradio2api/gr_types/models_parameters.py
gradio2api/gr_types/models_returns.py
gradio2api/utils/__init__.py
gradio2api/utils/gr_client_utils.py
gradio2api/utils/hash.py
gradio2api/utils/names.py
gradio2api-0.0.7.0.dist-info/METADATA
gradio2api-0.0.7.0.dist-info/WHEEL
gradio2api-0.0.7.0.dist-info/entry_points.txt
gradio2api-0.0.7.0.dist-info/top_level.txt
gradio2api-0.0.7.0.dist-info/RECORD
